cloneholio/__init__.py
cloneholio/__main__.py
cloneholio/errors.py
cloneholio/github.py
cloneholio/gitlab.py
cloneholio-0.15.1.dist-info/METADATA
cloneholio-0.15.1.dist-info/WHEEL
cloneholio-0.15.1.dist-info/entry_points.txt
cloneholio-0.15.1.dist-info/licenses/LICENSE
cloneholio-0.15.1.dist-info/RECORD
