Metadata-Version: 2.4
Name: cloneholio
Version: 0.15.1
Summary: I am cloneholio! I need syncing of my repos.
Project-URL: Homepage, https://gitlab.com/nvllsvm/cloneholio
Author-email: Andrew Rabert <ar@nullsum.net>
License: MIT
License-File: LICENSE
Classifier: Development Status :: 3 - Alpha
Classifier: Intended Audience :: Developers
Classifier: License :: OSI Approved :: MIT License
Classifier: Programming Language :: Python :: 3 :: Only
Requires-Python: >=3.10
Requires-Dist: arrow
Requires-Dist: gitpython
Requires-Dist: pygithub
Requires-Dist: requests
Requires-Dist: tqdm
